Metadata-Version: 2.1
Name: flexolink
Version: 1.0.1
Summary: hello hello hello, ko ko ko.
Home-page: https://gitee.com/huweiko/flexolink
Author: huwei
Author-email: hwboot@163.com
Maintainer: Wei Hu
Maintainer-email: hwboot@163.com
License: Flexolink License
Platform: linux
Classifier: Operating System :: OS Independent
Classifier: License :: OSI Approved :: MIT License
Classifier: Programming Language :: Python :: 3
Requires-Python: >=3
License-File: LICENSE
